colors_on_console/__init__.py
colors_on_console/cc.py
colors_on_console-0.0.1.dist-info/METADATA
colors_on_console-0.0.1.dist-info/WHEEL
colors_on_console-0.0.1.dist-info/licenses/LICENSE
colors_on_console-0.0.1.dist-info/RECORD
